py_moodle/__init__.py
py_moodle/__main__.py
py_moodle/assign.py
py_moodle/auth.py
py_moodle/category.py
py_moodle/course.py
py_moodle/draftfile.py
py_moodle/folder.py
py_moodle/label.py
py_moodle/module.py
py_moodle/page.py
py_moodle/resource.py
py_moodle/scorm.py
py_moodle/section.py
py_moodle/session.py
py_moodle/settings.py
py_moodle/upload.py
py_moodle/url.py
py_moodle/user.py
py_moodle/cli/__init__.py
py_moodle/cli/admin.py
py_moodle/cli/app.py
py_moodle/cli/categories.py
py_moodle/cli/courses.py
py_moodle/cli/folders.py
py_moodle/cli/modules.py
py_moodle/cli/pages.py
py_moodle/cli/resources.py
py_moodle/cli/sections.py
py_moodle/cli/urls.py
py_moodle/cli/users.py
python_moodle-0.0.1.dist-info/licenses/LICENSE
python_moodle-0.0.1.dist-info/METADATA
python_moodle-0.0.1.dist-info/WHEEL
python_moodle-0.0.1.dist-info/entry_points.txt
python_moodle-0.0.1.dist-info/top_level.txt
python_moodle-0.0.1.dist-info/RECORD
