Metadata-Version: 2.4
Name: python-moodle
Version: 0.0.1
Summary: Modern Moodle CLI tool
Author-email: Ernesto Serrano <info@ernesto.es>
Requires-Python: >=3.8
License-File: LICENSE
Requires-Dist: requests
Requires-Dist: beautifulsoup4
Requires-Dist: lxml
Requires-Dist: python-dotenv
Requires-Dist: typer[all]
Requires-Dist: rich==14.1.0
Dynamic: license-file
